openapi_client/__init__.py
openapi_client/api_client.py
openapi_client/api_response.py
openapi_client/configuration.py
openapi_client/exceptions.py
openapi_client/rest.py
openapi_client/api/__init__.py
openapi_client/api/auth_api.py
openapi_client/api/currency_api.py
openapi_client/api/expenses_api.py
openapi_client/api/group_api.py
openapi_client/api/incomes_api.py
openapi_client/api/invites_api.py
openapi_client/api/reports_api.py
openapi_client/api/transfers_api.py
openapi_client/api/users_api.py
openapi_client/api/wallets_api.py
openapi_client/models/__init__.py
openapi_client/models/api_user.py
openapi_client/models/currency.py
openapi_client/models/currency_rate.py
openapi_client/models/expense.py
openapi_client/models/expense_category.py
openapi_client/models/group.py
openapi_client/models/income.py
openapi_client/models/income_category.py
openapi_client/models/invite.py
openapi_client/models/paginated_api_user_list.py
openapi_client/models/paginated_currency_list.py
openapi_client/models/paginated_currency_rate_list.py
openapi_client/models/paginated_expense_category_list.py
openapi_client/models/paginated_expense_list.py
openapi_client/models/paginated_group_list.py
openapi_client/models/paginated_income_category_list.py
openapi_client/models/paginated_income_list.py
openapi_client/models/paginated_transfer_list.py
openapi_client/models/paginated_wallet_list.py
openapi_client/models/patched_api_user.py
openapi_client/models/patched_currency.py
openapi_client/models/patched_currency_rate.py
openapi_client/models/patched_expense.py
openapi_client/models/patched_expense_category.py
openapi_client/models/patched_group.py
openapi_client/models/patched_income.py
openapi_client/models/patched_income_category.py
openapi_client/models/patched_transfer.py
openapi_client/models/patched_wallet.py
openapi_client/models/report.py
openapi_client/models/signup.py
openapi_client/models/transfer.py
openapi_client/models/wallet.py
moneybox-1.0.0.dist-info/LICENSE
moneybox-1.0.0.dist-info/METADATA
moneybox-1.0.0.dist-info/WHEEL
moneybox-1.0.0.dist-info/top_level.txt
moneybox-1.0.0.dist-info/RECORD
