Metadata-Version: 2.1
Name: moneybox
Version: 1.0.0
Summary: MoneyBox
Home-page: https://github.com/moneybox-ai/django-moneybox
Author: Faithdev
Author-email: egorkaloskutov@yandex.ru
License-File: LICENSE
Requires-Dist: urllib3 <2.1.0,>=1.25.3
Requires-Dist: python-dateutil
Requires-Dist: pydantic <2,>=1.10.5
Requires-Dist: aenum
